[
    {
        "key": "datr",
        "value": "iQwoZn43Nkzyd6pjC2JWrxNn",
        "domain": "facebook.com",
        "path": "/",
        "hostOnly": false,
        "creation": "2024-04-26T12:19:38.450Z",
        "lastAccessed": "2024-04-26T12:19:38.450Z"
    },
    {
        "key": "sb",
        "value": "iQwoZlvlVqGuz1hS2dvdAWXA",
        "domain": "facebook.com",
        "path": "/",
        "hostOnly": false,
        "creation": "2024-04-26T12:19:38.450Z",
        "lastAccessed": "2024-04-26T12:19:38.450Z"
    },
    {
        "key": "locale",
        "value": "en_GB",
        "domain": "facebook.com",
        "path": "/",
        "hostOnly": false,
        "creation": "2024-04-26T12:19:38.450Z",
        "lastAccessed": "2024-04-26T12:19:38.450Z"
    },
    {
        "key": "vpd",
        "value": "v1%3B722x368x2.934335231781006",
        "domain": "facebook.com",
        "path": "/",
        "hostOnly": false,
        "creation": "2024-04-26T12:19:38.450Z",
        "lastAccessed": "2024-04-26T12:19:38.450Z"
    },
    {
        "key": "ps_n",
        "value": "1",
        "domain": "facebook.com",
        "path": "/",
        "hostOnly": false,
        "creation": "2024-04-26T12:19:38.450Z",
        "lastAccessed": "2024-04-26T12:19:38.450Z"
    },
    {
        "key": "ps_l",
        "value": "1",
        "domain": "facebook.com",
        "path": "/",
        "hostOnly": false,
        "creation": "2024-04-26T12:19:38.450Z",
        "lastAccessed": "2024-04-26T12:19:38.450Z"
    },
    {
        "key": "m_pixel_ratio",
        "value": "2.934335231781006",
        "domain": "facebook.com",
        "path": "/",
        "hostOnly": false,
        "creation": "2024-04-26T12:19:38.450Z",
        "lastAccessed": "2024-04-26T12:19:38.450Z"
    },
    {
        "key": "wd",
        "value": "369x722",
        "domain": "facebook.com",
        "path": "/",
        "hostOnly": false,
        "creation": "2024-04-26T12:19:38.450Z",
        "lastAccessed": "2024-04-26T12:19:38.450Z"
    },
    {
        "key": "fr",
        "value": "0TwAZdw0nuWa0TyAN.AWU0iIWy7NOJQLOfKohMhSPK-Xk.BmKAyJ..AAA.0.0.BmK5vS.AWV4IiXD6Gw",
        "domain": "facebook.com",
        "path": "/",
        "hostOnly": false,
        "creation": "2024-04-26T12:19:38.450Z",
        "lastAccessed": "2024-04-26T12:19:38.450Z"
    },
    {
        "key": "c_user",
        "value": "100069394770797",
        "domain": "facebook.com",
        "path": "/",
        "hostOnly": false,
        "creation": "2024-04-26T12:19:38.450Z",
        "lastAccessed": "2024-04-26T12:19:38.450Z"
    },
    {
        "key": "xs",
        "value": "9%3AK6tk1gZjxqh-nA%3A2%3A1714133970%3A-1%3A4489",
        "domain": "facebook.com",
        "path": "/",
        "hostOnly": false,
        "creation": "2024-04-26T12:19:38.450Z",
        "lastAccessed": "2024-04-26T12:19:38.450Z"
    },
    {
        "key": "fbl_st",
        "value": "100433077%3BT%3A28568899",
        "domain": "facebook.com",
        "path": "/",
        "hostOnly": false,
        "creation": "2024-04-26T12:19:38.450Z",
        "lastAccessed": "2024-04-26T12:19:38.450Z"
    },
    {
        "key": "wl_cbv",
        "value": "v2%3Bclient_version%3A2480%3Btimestamp%3A1714133973",
        "domain": "facebook.com",
        "path": "/",
        "hostOnly": false,
        "creation": "2024-04-26T12:19:38.450Z",
        "lastAccessed": "2024-04-26T12:19:38.450Z"
    },
    {
        "key": "m_page_voice",
        "value": "100069394770797",
        "domain": "facebook.com",
        "path": "/",
        "hostOnly": false,
        "creation": "2024-04-26T12:19:38.450Z",
        "lastAccessed": "2024-04-26T12:19:38.450Z"
    }
]
